banner88x31/Banner88x31.py
banner88x31/__init__.py
banner88x31-1.0.6.dist-info/METADATA
banner88x31-1.0.6.dist-info/WHEEL
banner88x31-1.0.6.dist-info/licenses/LICENSE
banner88x31-1.0.6.dist-info/RECORD
