Metadata-Version: 2.1
Name: banner88x31
Version: 1.0.6
Summary: a small package to retrieve 88x31 banners
Project-URL: Homepage, https://github.com/rudy3333/banner88x31
Project-URL: Bug Tracker, https://github.com/rudy3333/banner88x31/issues
Author-email: rudy3333 <mmax3163@gmail.com>
License-File: LICENSE
Classifier: License :: OSI Approved :: MIT License
Classifier: Operating System :: OS Independent
Classifier: Programming Language :: Python :: 3
Requires-Python: >=3.0
